{
    "1": {
        "content": [
            {
                "type": "text",
                "data": "Jeremy loses and finds his Teddy"
            },
            {
                "type": "image",
                "data": "..\\stories\\Jeremy loses and finds his Teddy\\@P1.png"
            },
            {
                "type": "image",
                "data": "..\\assets\\Title Circle.png"
            },
            {
                "type": "image",
                "data": "..\\assets\\Picolibo.png"
            }
        ]
    },
    "2": {
        "content": []
    },
    "3": {
        "content": []
    },
    "4": {
        "content": [
            {
                "type": "text",
                "data": "This story is specially created for Jeremy.\nIt teaches the concepts of"
            },
            {
                "type": "text",
                "data": "Friendship"
            },
            {
                "type": "image",
                "data": "..\\assets\\Blue Value Paint Stroke.png"
            }
        ]
    },
    "5": {
        "content": [
            {
                "type": "text",
                "data": "Published 2024 by PicoLibo, your personalised learning and nurturing companion.\n\nAll rights reserved.\n\nNo portion of this book may be reproduced in any form without written permission from the publisher or author."
            }
        ]
    },
    "6": {
        "content": [
            {
                "type": "text",
                "data": "In a big, old castle, there lived a boy named Jeremy."
            }
        ]
    },
    "7": {
        "content": [
            {
                "type": "image",
                "data": "..\\stories\\Jeremy loses and finds his Teddy\\@P1.png"
            }
        ]
    },
    "8": {
        "content": [
            {
                "type": "text",
                "data": "Jeremy loved his teddy bear."
            }
        ]
    },
    "9": {
        "content": [
            {
                "type": "image",
                "data": "..\\stories\\Jeremy loses and finds his Teddy\\@P2.png"
            }
        ]
    },
    "10": {
        "content": [
            {
                "type": "text",
                "data": "One day, Jeremy's teddy bear went missing."
            }
        ]
    },
    "11": {
        "content": [
            {
                "type": "image",
                "data": "..\\stories\\Jeremy loses and finds his Teddy\\@P3.png"
            }
        ]
    },
    "12": {
        "content": [
            {
                "type": "text",
                "data": "Jeremy looked under his bed, but it wasn't there."
            }
        ]
    },
    "13": {
        "content": [
            {
                "type": "image",
                "data": "..\\stories\\Jeremy loses and finds his Teddy\\@P4.png"
            }
        ]
    },
    "14": {
        "content": [
            {
                "type": "text",
                "data": "He checked behind the curtains, but it wasn't there either."
            }
        ]
    },
    "15": {
        "content": [
            {
                "type": "image",
                "data": "..\\stories\\Jeremy loses and finds his Teddy\\@P5.png"
            }
        ]
    },
    "16": {
        "content": [
            {
                "type": "text",
                "data": "Jeremy searched in the kitchen, but still no teddy bear."
            }
        ]
    },
    "17": {
        "content": [
            {
                "type": "image",
                "data": "..\\stories\\Jeremy loses and finds his Teddy\\@P6.png"
            }
        ]
    },
    "18": {
        "content": [
            {
                "type": "text",
                "data": "He climbed the stairs to the big, tall tower."
            }
        ]
    },
    "19": {
        "content": [
            {
                "type": "image",
                "data": "..\\stories\\Jeremy loses and finds his Teddy\\@P7.png"
            }
        ]
    },
    "20": {
        "content": [
            {
                "type": "text",
                "data": "At the top, Jeremy found a big, wooden chest."
            }
        ]
    },
    "21": {
        "content": [
            {
                "type": "image",
                "data": "..\\stories\\Jeremy loses and finds his Teddy\\@P8.png"
            }
        ]
    },
    "22": {
        "content": [
            {
                "type": "text",
                "data": "He opened the chest and saw his teddy bear inside!"
            }
        ]
    },
    "23": {
        "content": [
            {
                "type": "image",
                "data": "..\\stories\\Jeremy loses and finds his Teddy\\@P9.png"
            }
        ]
    },
    "24": {
        "content": [
            {
                "type": "text",
                "data": "Jeremy hugged his teddy bear tight."
            }
        ]
    },
    "25": {
        "content": [
            {
                "type": "image",
                "data": "..\\stories\\Jeremy loses and finds his Teddy\\@P10.png"
            }
        ]
    },
    "26": {
        "content": [
            {
                "type": "text",
                "data": "He felt happy to have his friend back."
            }
        ]
    },
    "27": {
        "content": [
            {
                "type": "image",
                "data": "..\\stories\\Jeremy loses and finds his Teddy\\@P11.png"
            }
        ]
    },
    "28": {
        "content": [
            {
                "type": "text",
                "data": "Jeremy learned that looking carefully helps find lost things."
            }
        ]
    },
    "29": {
        "content": [
            {
                "type": "image",
                "data": "..\\stories\\Jeremy loses and finds his Teddy\\@P12.png"
            }
        ]
    },
    "30": {
        "content": [
            {
                "type": "image",
                "data": "..\\assets\\Thinking Caps.png"
            },
            {
                "type": "text",
                "data": "Question 1: How do you think Jeremy felt when he couldn't find his teddy bear?\n\nQuestion 2: Why is it important to look carefully when we lose something?\n\nQuestion 3: How do you think Jeremy felt when he finally found his teddy bear?\n\nQuestion 4: What can you do to help someone who has lost something special to them?"
            }
        ]
    },
    "31": {
        "content": []
    },
    "32": {
        "content": []
    },
    "33": {
        "content": []
    },
    "34": {
        "content": [
            {
                "type": "text",
                "data": "Join Jeremy on an exciting quest through his big, old castle in search of his lost teddy bear. From peeking under beds to exploring the tallest tower, your little one will be captivated as Jeremy uncovers a valuable lesson about perseverance and careful searching. This heartwarming adventure is perfect for guiding 3-5 year olds through the emotions of losing and finding a cherished friend, wrapped in a simple yet enchanting tale."
            },
            {
                "type": "image",
                "data": "..\\stories\\Jeremy loses and finds his Teddy\\@P12.png"
            },
            {
                "type": "image",
                "data": "..\\assets\\Back Page Circle.png"
            },
            {
                "type": "image",
                "data": "..\\assets\\Picolibo.png"
            }
        ]
    },
    "story_name": "Jeremy loses and finds his Teddy"
}